{"cameraMode":{"drawMode":0,"name":"Shaded","section":"Shading Mode"},"sceneLighting":true,"audioPlay":false,"sceneViewState":{"showFog":true,"showMaterialUpdate":false,"showSkybox":true,"showFlares":true,"showImageEffects":true,"showParticleSystems":true},"in2DMode":false,"pivot":{"x":-2.5028557777404787,"y":-0.17613577842712403,"z":3.0965206623077394},"rotation":{"x":-0.19189020991325379,"y":0.22209671139717103,"z":-0.044632021337747577,"w":-0.9549132585525513},"size":7.020958423614502,"orthographic":false}